./.env.template
./.gitignore
./LICENSE
./PKG-INFO
./README.md
./main.py
./pyproject.toml
./requirements.txt
./saintdoresh-weather-mcp-claudedesktop_process.log
iflow_mcp_saintdoresh_weather_mcp_claudedesktop-0.1.0.dist-info/METADATA
iflow_mcp_saintdoresh_weather_mcp_claudedesktop-0.1.0.dist-info/WHEEL
iflow_mcp_saintdoresh_weather_mcp_claudedesktop-0.1.0.dist-info/entry_points.txt
iflow_mcp_saintdoresh_weather_mcp_claudedesktop-0.1.0.dist-info/licenses/LICENSE
iflow_mcp_saintdoresh_weather_mcp_claudedesktop-0.1.0.dist-info/RECORD
