Metadata-Version: 2.4
Name: iflow-mcp_saintdoresh_weather_mcp_claudedesktop
Version: 0.1.0
Summary: Weather MCP Tool for Claude Desktop - provides real-time weather data, forecasts, and historical weather information using the OpenWeatherMap API
License-File: LICENSE
Requires-Python: >=3.10
Requires-Dist: mcp>=1.3.0
Requires-Dist: python-dateutil>=2.8.2
Requires-Dist: python-dotenv>=1.0.0
Requires-Dist: requests>=2.28.0
